[{"date":"2022-04-04T21:36","name":"chart.png","mimetype":"image/png","size":10090,"description":"It's a chart of something","removed":false},{"date":"2022-04-04T21:39","name":"teste1.png","mimetype":"image/png","size":40623,"description":"Test of something","removed":true},{"date":"2022-04-04T21:40","name":"teste2.png","mimetype":"image/png","size":39682,"description":"Another test","removed":false},{"date":"2022-09-05T11:36","name":"SS.png","mimetype":"image/png","size":177443,"description":"segurança socieal","removed":true}]
